invoice/__init__.py
invoice/invoice.py
invoice_library-0.1.0.dist-info/LICENSE
invoice_library-0.1.0.dist-info/METADATA
invoice_library-0.1.0.dist-info/WHEEL
invoice_library-0.1.0.dist-info/top_level.txt
invoice_library-0.1.0.dist-info/RECORD
