Metadata-Version: 2.1
Name: invoice-library
Version: 0.1.0
Summary: A Django-based invoice generation library
Home-page: https://github.com/gvikrant9399/invoice-library
Author: Vikrant Ghode
Author-email: vikrantghode9399@gmail.com
License: MIT
Platform: UNKNOWN
Classifier: Development Status :: 3 - Alpha
Classifier: Intended Audience :: Developers
Classifier: License :: OSI Approved :: MIT License
Classifier: Programming Language :: Python :: 3
Classifier: Framework :: Django
License-File: LICENSE
Requires-Dist: Django>=3.2
